{
    "id": 626412,
    "name": "Alienoid 2: \u0110a Chi\u1ec1u H\u1ed7n Chi\u1ebfn(2024)",
    "release_year": "01/12/2024 (VN",
    "genre": "['Phim H\u00e0nh \u0110\u1ed9ng', 'Phim Gi\u1ea3 T\u01b0\u1ee3ng', 'Phim Phi\u00eau L\u01b0u']",
    "runtime": "2h 2m",
    "score": 66,
    "director": "Choi Dong-hoon",
    "status": "Released",
    "language": "Ti\u1ebfng H\u00e0n",
    "budget": "-",
    "revenue": "$10,824,208.00",
    "image": "https://media.themoviedb.org/t/p/w300_and_h450_bestv2/4RClncz0GTKPZzSAcAalHCw0h3g.jpg",
    "overview": "Ean (KIM Tae-ri) b\u1ecb m\u1eafc k\u1eb9t \u1edf qu\u00e1 kh\u1ee9 trong khi c\u1ed1 ng\u0103n ch\u1eb7n s\u1ef1 tr\u1ed1n tho\u00e1t c\u1ee7a nh\u1eefng t\u00f9 nh\u00e2n ngo\u00e0i h\u00e0nh tinh b\u1ecb nh\u1ed1t trong c\u01a1 th\u1ec3 con ng\u01b0\u1eddi. C\u00f4 cu\u1ed1i c\u00f9ng \u0111\u00e3 t\u00ecm th\u1ea5y G\u01b0\u01a1m Th\u1ea7n, c\u00f3 th\u1ec3 m\u1edf ra c\u00e1nh c\u1ed5ng xuy\u00ean th\u1eddi gian, v\u00e0 gi\u1edd ph\u1ea3i t\u00ecm Thunder (KIM Woo-bin) \u0111\u1ec3 tr\u1edf v\u1ec1 hi\u1ec7n t\u1ea1i. Trong khi \u0111\u00f3, Muruk (RYU Jun-yeol), ng\u01b0\u1eddi gi\u00fap Ean tho\u00e1t kh\u1ecfi nh\u1eefng t\u00ecnh hu\u1ed1ng nguy hi\u1ec3m, b\u1eaft \u0111\u1ea7u c\u1ea3m th\u1ea5y b\u1ea5t an khi anh nh\u1eadn th\u1ea5y s\u1ef1 hi\u1ec7n di\u1ec7n c\u1ee7a m\u1ed9t sinh v\u1eadt l\u1ea1 trong c\u01a1 th\u1ec3 m\u00ecnh. Tr\u1edf l\u1ea1i hi\u1ec7n t\u1ea1i, s\u1ef1 ph\u00e1t t\u00e1n c\u1ee7a kh\u00ed haava b\u1edfi Th\u1ee7 L\u0129nh, k\u1ebb l\u00e3nh \u0111\u1ea1o nh\u1eefng t\u00f9 nh\u00e2n ngo\u00e0i h\u00e0nh tinh \u0111\u00e3 khi\u1ebfn h\u00e0ng ng\u00e0n ng\u01b0\u1eddi ch\u1ebft. Min Gaelin (LEE Ha-nee) ng\u01b0\u1eddi t\u00ecnh c\u1edd ch\u1ee9ng ki\u1ebfn \u0111i\u1ec1u n\u00e0y \u0111\u00e3 nh\u1eadn ra r\u1eb1ng \u0111\u00e2y ch\u1ec9 l\u00e0 kh\u1edfi \u0111\u1ea7u...",
    "metadata": {
        "page": 122,
        "index": 8,
        "time_craw": "2025-04-08 18:59:28"
    }
}