{
    "id": 321883,
    "name": "Minecraft: Into the Nether(2015)",
    "release_year": "01/27/2015 (US",
    "genre": "['Phim T\u00e0i Li\u1ec7u']",
    "runtime": "1h 17m",
    "score": 79,
    "director": "Billy Simpson",
    "status": "Released",
    "language": "Ti\u1ebfng Anh",
    "budget": "-",
    "revenue": "-",
    "image": "https://media.themoviedb.org/t/p/w300_and_h450_bestv2/vLci7Om940xXupc4kUPTC2JoGWW.jpg",
    "overview": "Minecraft. The game that took the world by storm. Follow the story of how the Minecraft phenomenon has ploughed through the 21st century selling over 54 million copies worldwide on a multitude of platforms engaging an audience in the millions which is still continuing to grow. The game boasts the biggest digital world in gaming history with a fan base stretching to every corner of the globe. Youtube viewing numbers have grown and online participation has tripled over the last few years creating a new industry for enthusiastic gamers. Vast communities have been brought together through it's educational impact, YouTube celebrities, festivals and game events pushing the boundaries of technology and creativity to the limits.",
    "metadata": {
        "page": 4,
        "index": 10,
        "time_craw": "2025-04-08 15:13:51"
    }
}