{
    "id": 1141182,
    "name": "Ch\u1ebft M\u1ed9t M\u00ecnh(2024)",
    "release_year": "09/27/2024 (CA",
    "genre": "['Phim Kinh D\u1ecb', 'Phim G\u00e2y C\u1ea5n', 'Phim Khoa H\u1ecdc Vi\u1ec5n T\u01b0\u1edfng']",
    "runtime": "1h 31m",
    "score": 59,
    "director": "Lowell Dean",
    "status": "Released",
    "language": "Ti\u1ebfng Anh",
    "budget": "-",
    "revenue": "-",
    "image": "https://media.themoviedb.org/t/p/w300_and_h450_bestv2/dQdIj2OYELhLzECWONY932wGRxA.jpg",
    "overview": "B\u1ed9 phim k\u1ec3 v\u1ec1 m\u1ed9t ch\u00e0ng trai tr\u1ebb b\u1ecb m\u1ea5t tr\u00ed nh\u1edb, anh ph\u1ea3i h\u1ee3p t\u00e1c v\u1edbi m\u1ed9t ng\u01b0\u1eddi s\u1ed1ng s\u00f3t c\u1ee9ng r\u1eafn trong m\u1ed9t cu\u1ed9c b\u00f9ng ph\u00e1t gi\u1ed1ng nh\u01b0 zombie \u0111\u1ec3 t\u00ecm ki\u1ebfm b\u1ea1n g\u00e1i c\u1ee7a m\u00ecnh",
    "metadata": {
        "page": 73,
        "index": 7,
        "time_craw": "2025-04-08 17:26:37"
    }
}