{
    "id": 948,
    "name": "Halloween(1978)",
    "release_year": "10/25/1978 (US",
    "genre": "['Phim Kinh D\u1ecb', 'Phim G\u00e2y C\u1ea5n']",
    "runtime": "1h 31m",
    "score": 76,
    "director": "John Carpenter",
    "status": "Released",
    "language": "Ti\u1ebfng Anh",
    "budget": "$325,000.00",
    "revenue": "$70,260,597.00",
    "image": "https://media.themoviedb.org/t/p/w300_and_h450_bestv2/wijlZ3HaYMvlDTPqJoTCWKFkCPU.jpg",
    "overview": "Bu\u1ed5i t\u1ed1i ng\u00e0y 31 th\u00e1ng 10 n\u0103m 1963, c\u1eadu b\u00e9 6 tu\u1ed5i Michael Myers \u0111\u00e2m c\u00f4 ch\u1ecb 15 tu\u1ed5i \u0111\u1ebfn ch\u1ebft. Sau khi gia \u0111\u00ecnh c\u1eadu b\u00e9 tr\u1edf v\u1ec1 nh\u00e0 \u0111\u00e3 ph\u00e1t hi\u1ec7n ra v\u1ee5 vi\u1ec7c v\u00e0 l\u1eadp t\u1ee9c \u0111\u01b0a h\u1eafn v\u00e0o vi\u1ec7n t\u00e2m th\u1ea7n \u0111i\u1ec1u tr\u1ecb \u0111\u1eb7c bi\u1ec7t d\u01b0\u1edbi s\u1ef1 theo d\u00f5i c\u1ee7a b\u00e1c s\u0129 Loomis.Ng\u00e0y 30 th\u00e1ng 10 n\u0103m 1978, khi Michael tr\u00f2n 21 tu\u1ed5i, b\u00e1c s\u0129 Loomis quy\u1ebft \u0111\u1ecbnh c\u00f3 1 bu\u1ed5i ki\u1ec3m tra xem h\u1eafn \u0111\u00e3 ho\u00e0n to\u00e0n b\u00ecnh ph\u1ee5c hay ch\u01b0a nh\u01b0ng Michael \u0111\u00e3 t\u1ea5n c\u00f4ng m\u1ecdi ng\u01b0\u1eddi v\u00e0 b\u1ecf tr\u1ed1n. H\u1eafn \u0111\u00e3 tr\u1edf v\u1ec1 qu\u00ea nh\u00e0 v\u00e0 ti\u1ebfn h\u00e0nh cu\u1ed9c th\u1ea3m s\u00e1t \u0111\u1eabm m\u00e1u trong \u0111\u00eam Halloween\u2026",
    "metadata": {
        "page": 65,
        "index": 9,
        "time_craw": "2025-04-08 17:11:50"
    }
}