{
    "id": 481848,
    "name": "Ti\u1ebfng G\u1ecdi N\u01a1i Hoang D\u00e3(2020)",
    "release_year": "02/21/2020 (VN",
    "genre": "['Phim Phi\u00eau L\u01b0u', 'Phim Gia \u0110\u00ecnh', 'Phim Ch\u00ednh K\u1ecbch']",
    "runtime": "1h 40m",
    "score": 75,
    "director": "Chris Sanders",
    "status": "Released",
    "language": "Ti\u1ebfng Anh",
    "budget": "$109,000,000.00",
    "revenue": "$111,200,000.00",
    "image": "https://media.themoviedb.org/t/p/w300_and_h450_bestv2/5EBWSyLfsmzIU06464PYV3jH75C.jpg",
    "overview": "The Call of the Wild l\u00e0 m\u1ed9t b\u1ed9 phim phi\u00eau l\u01b0u s\u1eafp ra m\u1eaft c\u1ee7a M\u1ef9 d\u1ef1a tr\u00ean ti\u1ec3u thuy\u1ebft c\u00f9ng t\u00ean c\u1ee7a Jack London 1903 v\u00e0 b\u1ed9 phim chuy\u1ec3n th\u1ec3 n\u0103m 1935 tr\u01b0\u1edbc \u0111\u00e2y c\u1ee7a Twentieth Century Pictures.",
    "metadata": {
        "page": 65,
        "index": 10,
        "time_craw": "2025-04-08 17:11:54"
    }
}