{
    "id": 1247019,
    "name": "Tee Yod: Qu\u1ef7 \u0102n T\u1ea1ng 2(2024)",
    "release_year": "10/10/2024 (TH",
    "genre": "['Phim Kinh D\u1ecb', 'Phim G\u00e2y C\u1ea5n', 'Phim H\u00e0nh \u0110\u1ed9ng']",
    "runtime": "1h 52m",
    "score": 70,
    "director": "Taweewat Wantha",
    "status": "Released",
    "language": "Ti\u1ebfng Th\u00e1i",
    "budget": "-",
    "revenue": "$4,210,676.00",
    "image": "https://media.themoviedb.org/t/p/w300_and_h450_bestv2/9G0czCAjBlZvrfmNhTPRyA14Ktj.jpg",
    "overview": "Ba n\u0103m sau c\u00e1i ch\u1ebft c\u1ee7a Yam, Yak v\u1eabn ti\u1ebfp t\u1ee5c s\u0103n l\u00f9ng linh h\u1ed3n b\u00ed \u1ea9n m\u1eb7c \u00e1o cho\u00e0ng \u0111en. G\u1eb7p m\u1ed9t c\u00f4 g\u00e1i c\u00f3 tri\u1ec7u ch\u1ee9ng gi\u1ed1ng Yam, Yak ph\u00e1t hi\u1ec7n ra ng\u01b0\u1eddi b\u1ea3o v\u1ec7 linh h\u1ed3n, ph\u00e1p s\u01b0 \u1ea9n d\u1eadt Puang, s\u1ed1ng trong m\u1ed9t khu r\u1eebng \u0111\u1ea7y nguy hi\u1ec3m. Gi\u1eefa nh\u1eefng ph\u00e9p thu\u1eadt ma qu\u1ef7 v\u00e0 nh\u1eefng sinh v\u1eadt nguy hi\u1ec3m. Khi h\u1ecd \u0111u\u1ed5i theo linh h\u1ed3n m\u1eb7c \u00e1o cho\u00e0ng \u0111en, ti\u1ebfng k\u00eau \u0111\u1ea7y \u00e1m \u1ea3nh c\u1ee7a Tee Yod s\u1eafp quay tr\u1edf l\u1ea1i m\u1ed9t l\u1ea7n n\u1eefa...",
    "metadata": {
        "page": 9,
        "index": 17,
        "time_craw": "2025-04-08 15:24:02"
    }
}