{
    "id": 1380415,
    "name": "The Last Supper(2025)",
    "release_year": "03/14/2025 (US",
    "genre": "['Phim Ch\u00ednh K\u1ecbch']",
    "runtime": "1h 54m",
    "score": 59,
    "director": "Mauro Borrelli",
    "status": "Released",
    "language": "Ti\u1ebfng Anh",
    "budget": "$8,000,000.00",
    "revenue": "$6,254,291.00",
    "image": "https://media.themoviedb.org/t/p/w300_and_h450_bestv2/fulEdvN5u6mIpwig7HcBnYpkJEQ.jpg",
    "overview": "In the days leading to betrayal, a gathering of disciples unravels into a web of secrets and hidden motives. As tensions simmer beneath the surface, trust is tested, and loyalty is questioned. The Last Supper becomes a night where nothing is as it seems, and every glance hides a deeper truth.",
    "metadata": {
        "page": 80,
        "index": 4,
        "time_craw": "2025-04-08 17:39:36"
    }
}