{
    "id": 644,
    "name": "Tr\u00ed Tu\u1ec7 Nh\u00e2n T\u1ea1o(2001)",
    "release_year": "06/29/2001 (US",
    "genre": "['Phim Ch\u00ednh K\u1ecbch', 'Phim Khoa H\u1ecdc Vi\u1ec5n T\u01b0\u1edfng', 'Phim Phi\u00eau L\u01b0u']",
    "runtime": "2h 26m",
    "score": 70,
    "director": "Steven Spielberg",
    "status": "Released",
    "language": "Ti\u1ebfng Anh",
    "budget": "$100,000,000.00",
    "revenue": "$235,926,552.00",
    "image": "https://media.themoviedb.org/t/p/w300_and_h450_bestv2/8MZSGX5JORoO72EfuAEcejH5yHn.jpg",
    "overview": "Trong t\u01b0\u01a1ng lai, con ng\u01b0\u1eddi t\u1ea1o ra m\u1ed9t th\u1ebf h\u1ec7 robot m\u1edbi bi\u1ebft t\u01b0 duy, ho\u1ea1t \u0111\u1ed9ng nh\u01b0 con ng\u01b0\u1eddi, th\u1eadm ch\u00ed c\u00f3 nh\u1eefng t\u00ecnh c\u1ea3m v\u00e0 c\u1ea3m x\u00fac y h\u1ec7t con ng\u01b0\u1eddi. \u1ede m\u1ed9t n\u01a1i kh\u00e1c, v\u1ee3 ch\u1ed3ng Monica v\u00e0 Henry Swinton \u0111au kh\u1ed5 trong tuy\u1ec7t v\u1ecdng khi c\u1eadu con trai Martin \u0111ang l\u00e2m b\u1ec7nh n\u1eb7ng. Kh\u00f4ng cam l\u00f2ng nh\u00ecn v\u1ee3 s\u1ea7u th\u1ea3m, Henry \u0111\u1eb7t s\u1ea3n xu\u1ea5t m\u1ed9t robot tr\u1ebb em v\u1ec1 b\u1ea7u b\u1ea1n v\u1edbi v\u1ee3 v\u1edbi \u0111i\u1ec1u ki\u1ec7n, s\u1ebd ph\u1ea3i ho\u00e0n tr\u1ea3 s\u1ea3n ph\u1ea9m cho nh\u00e0 s\u1ea3n xu\u1ea5t n\u1ebfu kh\u00f4ng c\u00f3 nhu c\u1ea7u s\u1eed d\u1ee5ng.  Robot c\u00f3 t\u00ean l\u00e0 David. Kh\u00f4ng ai ph\u00e1t hi\u1ec7n ra c\u1eadu kh\u00f4ng ph\u1ea3i ng\u01b0\u1eddi th\u1eadt b\u1edfi David l\u00e0 m\u1ed9t ng\u01b0\u1eddi m\u00e1y ho\u00e0n h\u1ea3o. Nh\u01b0ng b\u00e0 Monica v\u1eabn kh\u00f4ng th\u1ec3 coi c\u1eadu l\u00e0 con. D\u1ea7n d\u1ea7n, b\u1eb1ng t\u00ecnh c\u1ea3m thi\u1ebft tha, \u00e1nh m\u1eaft bu\u1ed3n b\u00e3 \u0111\u1ebfn kh\u1eafc kho\u1ea3i, David l\u00e0m cho tr\u00e1i tim \u0111au kh\u1ed5 c\u1ee7a m\u1eb9 ph\u1ea3i tan ch\u1ea3y\u2026",
    "metadata": {
        "page": 79,
        "index": 10,
        "time_craw": "2025-04-08 17:38:15"
    }
}