{
    "id": 15255,
    "name": "Quy\u1ebft \u0110\u1ea5u 2: K\u1ebb \u0110\u1ee9ng Cu\u1ed1i C\u00f9ng(2006)",
    "release_year": "04/11/2006 (US",
    "genre": "['Phim H\u00e0nh \u0110\u1ed9ng', 'Phim H\u00ecnh S\u1ef1', 'Phim G\u00e2y C\u1ea5n', 'Phim Ch\u00ednh K\u1ecbch']",
    "runtime": "1h 33m",
    "score": 73,
    "director": "Isaac Florentine",
    "status": "Released",
    "language": "Ti\u1ebfng Anh",
    "budget": "$8,000,000.00",
    "revenue": "$1,361.00",
    "image": "https://media.themoviedb.org/t/p/w300_and_h450_bestv2/2gMCokqpIJoh6u5o06LlOZWsI3k.jpg",
    "overview": "Nh\u00e0 v\u00f4 \u0111\u1ecbch quy\u1ec1n anh Chambers b\u1ecb b\u1eaft giam trong m\u1ed9t nh\u00e0 t\u00f9 \u1edf Nga v\u00e0 anh b\u1ecb b\u1eaft bu\u1ed9c ph\u1ea3i tham gia c\u00e1c tr\u1eadn \u0111\u1ea5m b\u1ed1c \u0111\u1ea7y b\u1ea1o l\u1ef1c. Kh\u00f4ng m\u1ed9t lu\u1eadt l\u1ec7 n\u00e0o r\u00e0ng bu\u1ed9c gi\u1eefa c\u00e1c tr\u1eadn \u0111\u1ea5u, th\u1eafng thua \u0111\u01b0\u1ee3c quy\u1ebft \u0111\u1ecbnh b\u1eb1ng s\u1ef1 s\u1ed1ng v\u00e0 c\u00e1i ch\u1ebft, v\u1edbi nh\u1eefng kh\u1ea3 n\u0103ng v\u00e0 kinh nghi\u1ec7m quy\u1ec1n anh c\u1ee7a m\u00ecnh, Chambers ph\u1ea3i \u0111\u1ed1i m\u1eb7t v\u1edbi nh\u1eefng t\u00ean v\u00f5 s\u0129 to l\u1edbn v\u00e0 b\u1ea1o l\u1ef1c.",
    "metadata": {
        "page": 97,
        "index": 13,
        "time_craw": "2025-04-08 18:12:50"
    }
}