{
    "id": 1167366,
    "name": "Uranus 2324(2024)",
    "release_year": "07/04/2024 (TH",
    "genre": "['Phim L\u00e3ng M\u1ea1n', 'Phim Ch\u00ednh K\u1ecbch', 'Phim Khoa H\u1ecdc Vi\u1ec5n T\u01b0\u1edfng']",
    "runtime": "2h 28m",
    "score": 62,
    "director": "Thanadol Nuansut",
    "status": "Released",
    "language": "Ti\u1ebfng Th\u00e1i",
    "budget": "-",
    "revenue": "-",
    "image": "https://media.themoviedb.org/t/p/w300_and_h450_bestv2/zTD9HytRG1nfP5pdOAYmPyXj05d.jpg",
    "overview": "G\u1eafn b\u00f3 t\u1eeb thu\u1edf thi\u1ebfu th\u1eddi nh\u01b0ng r\u1ed3i chia l\u00eca v\u00ec bi k\u1ecbch, m\u1ed9t phi h\u00e0nh gia v\u00e0 m\u1ed9t th\u1ee3 l\u1eb7n t\u1ef1 do b\u1ebb cong c\u00e1c \u0111\u1ecbnh lu\u1eadt v\u1ec1 kh\u00f4ng gian v\u00e0 th\u1eddi gian \u0111\u1ec3 t\u00ecm c\u00e1ch \u1edf b\u00ean nhau l\u1ea7n n\u1eefa.",
    "metadata": {
        "page": 2,
        "index": 9,
        "time_craw": "2025-04-08 15:09:56"
    }
}