{
    "id": 11360,
    "name": "Ch\u00fa Voi Bi\u1ebft Bay(1941)",
    "release_year": "10/31/1941 (US",
    "genre": "['Phim Ho\u1ea1t H\u00ecnh', 'Phim Gia \u0110\u00ecnh']",
    "runtime": "1h 4m",
    "score": 70,
    "director": "Norman Ferguson",
    "status": "Released",
    "language": "Ti\u1ebfng Anh",
    "budget": "$812,000.00",
    "revenue": "$1,600,000.00",
    "image": "https://media.themoviedb.org/t/p/w300_and_h450_bestv2/hKDdllslMtsU9JixAv5HR9biXlp.jpg",
    "overview": "Dumbo - ch\u00fa voi con \u0111\u01b0\u1ee3c sinh ra v\u00e0 l\u1edbn l\u00ean trong m\u1ed9t g\u00e1nh xi\u1ebfc. Ngay t\u1eeb khi ra \u0111\u1eddi, c\u1eadu \u0111\u00e3 b\u1ecb c\u00e1c con voi kh\u00e1c trong \u0111o\u00e0n c\u01b0\u1eddi ch\u00ea v\u00ec c\u00f3 \u0111\u00f4i tai to l\u1edbn b\u1ea5t th\u01b0\u1eddng, b\u1ecb \u0111\u1eb7t t\u00ean l\u00e0 Dumbo (ngh\u0129a l\u00e0 ngu ng\u1ed1c). Ngo\u00e0i voi m\u1eb9 Jumbo, ch\u1ec9 c\u00f3 ch\u00fa chu\u1ed9t nh\u1ecf Timothy Q l\u00e0 quan t\u00e2m v\u00e0 b\u1ea7u b\u1ea1n v\u1edbi Dumbo. Ch\u00fa chu\u1ed9t n\u00e0y lu\u00f4n th\u00f4ng c\u1ea3m v\u1edbi ho\u00e0n c\u1ea3nh c\u1ee7a Dumbo, v\u00ec th\u1ebf m\u00e0 c\u1eadu ta \u0111\u00e3 quy\u1ebft \u0111\u1ecbnh s\u1ebd l\u00e0m Dumbo vui v\u1ebb tr\u1edf l\u1ea1i, t\u1ef1 \u0111\u1ec1 nhi\u1ec7m m\u00ecnh s\u1ebd l\u00e0m c\u1ed1 v\u1ea5n v\u00e0 b\u1ea3o v\u1ec7 cho Dumbo sau n\u00e0y v\u00e0 m\u00e3i m\u00e3i. T\u1eeb \u0111\u00f3 h\u1ecd \u0111\u00e3 tr\u1edf th\u00e0nh m\u1ed9t \u0111\u00f4i b\u1ea1n th\u00e2n tri k\u1ec9. Trong m\u1ed9t l\u1ea7n bi\u1ec3u di\u1ec5n xi\u1ebfc tr\u00ean m\u1ed9t t\u00f2a nh\u00e0 cao \u1ed1c, v\u00ec g\u1eb7p ph\u1ea3i nh\u1eefng s\u1ef1 c\u1ed1 kh\u00f4ng may m\u00e0 Dumbo \u0111\u00e3 b\u1ecb tr\u01b0\u1ee3t ng\u00e3, nh\u01b0ng c\u0169ng ch\u00ednh t\u1eeb \u0111\u00f3 m\u00e0 ch\u00fa voi n\u00e0y \u0111\u00e3 d\u00f9ng ch\u00ednh \u0111\u00f4i tai \u0111\u1ec3 bay l\u00ean. V\u00e0 t\u1eeb \u0111\u00f3 tr\u1edf \u0111i Dumbo tr\u1edf n\u00ean n\u1ed5i ti\u1ebfng tr\u00ean c\u00e1c ph\u01b0\u01a1ng ti\u1ec7n truy\u1ec1n th\u00f4ng, Timothy tr\u1edf th\u00e0nh qu\u1ea3n l\u00fd c\u1ee7a c\u1eadu, Dumbo v\u00e0 b\u00e0 Jumbo c\u00f3 \u0111\u01b0\u1ee3c m\u1ed9t toa t\u00e0u c\u1ee7a ri\u00eang h\u1ecd tr\u00ean t\u00e0u xi\u1ebfc...",
    "metadata": {
        "page": 65,
        "index": 20,
        "time_craw": "2025-04-08 17:12:49"
    }
}