{
    "id": 4232,
    "name": "Ti\u1ebfng Th\u00e9t(1996)",
    "release_year": "12/20/1996 (US",
    "genre": "['Phim H\u00ecnh S\u1ef1', 'Phim Kinh D\u1ecb', 'Phim B\u00ed \u1ea8n']",
    "runtime": "1h 52m",
    "score": 74,
    "director": "Wes Craven",
    "status": "Released",
    "language": "Ti\u1ebfng Anh",
    "budget": "$14,000,000.00",
    "revenue": "$173,046,663.00",
    "image": "https://media.themoviedb.org/t/p/w300_and_h450_bestv2/26MzHQ8yoGWBk9NdLEQyzhMSm6z.jpg",
    "overview": "Sidney v\u00e0 nh\u00f3m b\u1ea1n c\u1ee7a c\u00f4 b\u1ecb m\u1ed9t t\u00ean s\u00e1t nh\u00e2n trong m\u1eb7t n\u1ea1t tr\u1eb1ng \u0111e do\u1ea1. M\u1ecdi nghi ng\u1edd \u0111\u1ed5 v\u1ec1 ng\u01b0\u1eddi y\u00eau c\u1ee7a c\u00f4. C\u00f4 ngh\u0129 chuy\u1ec7n n\u00e0y c\u00f3 li\u00ean quan \u0111\u1ebfn c\u00e1i ch\u1ebft c\u1ee7a m\u1eb9 c\u00f4 c\u00e1ch \u0111\u00e2y m\u1ed9t n\u0103m. R\u1ed3i t\u1eebng ng\u01b0\u1eddi b\u1ea1n c\u1ee7a c\u00f4 b\u1ecb gi\u1ebft m\u1ed9t c\u00e1ch b\u00ed \u1ea9n.",
    "metadata": {
        "page": 38,
        "index": 8,
        "time_craw": "2025-04-08 16:19:10"
    }
}