{
    "id": 534643,
    "name": "Tabu(2010)",
    "release_year": "05/01/2010 (US",
    "genre": "[]",
    "runtime": "25m",
    "score": 20,
    "director": "Vincent Coen",
    "status": "Released",
    "language": "Ti\u1ebfng Anh",
    "budget": "-",
    "revenue": "-",
    "image": "https://media.themoviedb.org/t/p/w300_and_h450_bestv2/ekfLoHZdFO7YiEJNQbxPcfesOUX.jpg",
    "overview": "Young musician goes on vacation with his family. He meets an older woman there, they fall in love and spend a passionate night together. The next day, his family has something shocking to tell him.",
    "metadata": {
        "page": 120,
        "index": 2,
        "time_craw": "2025-04-08 18:55:10"
    }
}