{
    "id": 1151506,
    "name": "From Good to the Hood(2024)",
    "release_year": "12/05/2024 (ES",
    "genre": "['Phim H\u00e0i']",
    "runtime": NaN,
    "score": 60,
    "director": "Mar Olid",
    "status": "Released",
    "language": "Ti\u1ebfng T\u00e2y Ban Nh\u00e0 ki\u1ec3u Cax-ti-le",
    "budget": "-",
    "revenue": "-",
    "image": "https://media.themoviedb.org/t/p/w300_and_h450_bestv2/n9UejLgJi5HzRyEXEH7l5CUNKm4.jpg",
    "overview": "Cheating the tax man was just too tempting for Andr\u00e9s. Besides, what are the chances of him getting caught? Well, as it turns out, pretty high! And that\u2019s exactly what happens when a couple of tax inspectors turn up at his company to inform him that he owes the IRS a lot of money.",
    "metadata": {
        "page": 8,
        "index": 7,
        "time_craw": "2025-04-08 15:21:14"
    }
}