{
    "id": 1059128,
    "name": "\u0110\u1ed3ng T\u00ednh(2024)",
    "release_year": "11/27/2024 (US",
    "genre": "['Phim Ch\u00ednh K\u1ecbch', 'Phim L\u00e3ng M\u1ea1n']",
    "runtime": "2h 16m",
    "score": 67,
    "director": "Luca Guadagnino",
    "status": "Released",
    "language": "Ti\u1ebfng Anh",
    "budget": "$53,400,000.00",
    "revenue": "$5,450,715.00",
    "image": "https://media.themoviedb.org/t/p/w300_and_h450_bestv2/xe4b2TMciLKA1C0JlhWxb4ENLln.jpg",
    "overview": "L\u1ea5y b\u1ed1i c\u1ea3nh nh\u1eefng n\u0103m 1950 t\u1ea1i th\u00e0nh ph\u1ed1 Mexico, QUEER l\u00e0 c\u00e2u chuy\u1ec7n v\u00e0 h\u00e0nh tr\u00ecnh \u0111\u1ea7y k\u1ef3 \u1ea3o c\u1ee7a William Lee, m\u1ed9t g\u00e3 ng\u01b0\u1eddi M\u1ef9 cu\u1ed1i tu\u1ed5i t\u1ee9 tu\u1ea7n, s\u1ed1ng m\u1ed9t cu\u1ed9c \u0111\u1eddi l\u1eb7p \u0111i l\u1eb7p l\u1ea1i t\u1eeb qu\u00e1n bar n\u00e0y sang qu\u00e1n bar kh\u00e1c. S\u1ef1 xu\u1ea5t hi\u1ec7n c\u1ee7a ch\u00e0ng trai tr\u1ebb Eugene Allerton t\u1ef1a nh\u01b0 m\u1ed9t l\u00e0n gi\u00f3 m\u1edbi. Anh ch\u00e0ng b\u00ed \u1ea9n v\u00e0 kh\u00f3 n\u1eafm b\u1eaft t\u00e2m t\u01b0 \u1ea5y \u0111\u00e3 khu\u1ea5y \u0111\u1ed9ng v\u00e0 l\u00e0m thay \u0111\u1ed5i c\u00e1ch nh\u00ecn nh\u1eadn th\u1ebf gi\u1edbi, th\u00fac \u0111\u1ea9y mong mu\u1ed1n thi\u1ebft l\u1eadp m\u1ed9t m\u1ed1i quan h\u1ec7 c\u00f3 \u00fd ngh\u0129a v\u1edbi ai \u0111\u00f3 c\u1ee7a Lee.M\u1ed9t b\u1eefa ti\u1ec7c th\u1ecb gi\u00e1c \u0111\u1ea7y m\u00e3n nh\u00e3n \u1ea9n trong nh\u1eefng khung h\u00ecnh \u0111i\u1ec7n \u1ea3nh \"\u0111\u1eadm ch\u1ea5t Guadagnino nh\u1ea5t t\u1eeb tr\u01b0\u1edbc \u0111\u1ebfn nay\".",
    "metadata": {
        "page": 50,
        "index": 12,
        "time_craw": "2025-04-08 16:42:18"
    }
}