{
    "id": 33602,
    "name": "Chuy\u1ec7n C\u1ee7a C\u00f4 Temple Grandin(2010)",
    "release_year": "02/06/2010 (US",
    "genre": "['Phim Ch\u00ednh K\u1ecbch', 'Phim L\u1ecbch S\u1eed']",
    "runtime": "1h 48m",
    "score": 78,
    "director": "Temple Grandin",
    "status": "Released",
    "language": "Ti\u1ebfng Anh",
    "budget": "-",
    "revenue": "-",
    "image": "https://media.themoviedb.org/t/p/w300_and_h450_bestv2/7zcylW4oBLAaShlnUNfrtRZy3Iu.jpg",
    "overview": "M\u1ed9t c\u00f4 g\u00e1i m\u1eafc ch\u1ee9ng t\u1ef1 k\u1ef7, Temple Grandin, \u0111\u00e3 v\u01b0\u1ee3t qua nh\u1eefng h\u1ea1n ch\u1ebf do t\u00ecnh tr\u1ea1ng c\u1ee7a c\u00f4 \u1ea5y \u00e1p \u0111\u1eb7t v\u00e0 tr\u1edf th\u00e0nh m\u1ed9t chuy\u00ean gia trong l\u0129nh v\u1ef1c ch\u0103n nu\u00f4i.",
    "metadata": {
        "page": 122,
        "index": 3,
        "time_craw": "2025-04-08 18:58:59"
    }
}