{
    "id": 1028703,
    "name": "The OctoGames(2022)",
    "release_year": "10/07/2022 (US",
    "genre": "['Phim G\u00e2y C\u1ea5n', 'Phim H\u00e0nh \u0110\u1ed9ng', 'Phim Kinh D\u1ecb']",
    "runtime": "1h 28m",
    "score": 54,
    "director": "Aaron Mirtes",
    "status": "Released",
    "language": "Ti\u1ebfng Anh",
    "budget": "-",
    "revenue": "-",
    "image": "https://media.themoviedb.org/t/p/w300_and_h450_bestv2/qGz5rffXhegQH5PGUDiObqoOt06.jpg",
    "overview": "Eight contestants compete in eight deadly, classic children's games. They seek fame beyond their wildest dreams, competing for the chance to take over the YouTube channel of the famous yet elusive masked content creator known only as \"JaxPro\".",
    "metadata": {
        "page": 113,
        "index": 14,
        "time_craw": "2025-04-08 18:43:03"
    }
}