{
    "id": 525,
    "name": "T\u00ecnh Anh Em(1980)",
    "release_year": "06/16/1980 (US",
    "genre": "['Phim Nh\u1ea1c', 'Phim H\u00e0i', 'Phim H\u00e0nh \u0110\u1ed9ng', 'Phim H\u00ecnh S\u1ef1']",
    "runtime": "2h 13m",
    "score": 77,
    "director": "John Landis",
    "status": "Released",
    "language": "Ti\u1ebfng Anh",
    "budget": "$27,000,000.00",
    "revenue": "$115,229,890.00",
    "image": "https://media.themoviedb.org/t/p/w300_and_h450_bestv2/rhYJKOt6UrQq7JQgLyQcSWW5R86.jpg",
    "overview": "V\u1edbi \u00fd ngh\u0129 s\u1ebd ngh\u1ec9 ng\u01a1i sau khi v\u1eeba ra t\u00f9, anh em nh\u00e0 Blues, Jake v\u00e0 Elwood, \u0111\u00e3 quy\u1ebft \u0111\u1ecbnh t\u1edbi th\u0103m l\u1ea1i tr\u1ea1i tr\u1ebb m\u1ed3 c\u00f4i \u1edf Chicago - n\u01a1i h\u1ecd \u0111\u00e3 \u0111\u01b0\u1ee3c nu\u00f4i l\u1edbn. Nh\u01b0ng khi t\u1edbi \u0111\u00e2y, h\u1ecd bi\u1ebft r\u1eb1ng tr\u1ea1i tr\u1ebb \u0111\u00e3 m\u1ea5t ngu\u1ed3n h\u1ed7 tr\u1ee3 v\u00e0 s\u1ebd b\u1ecb b\u00e1n. C\u00e1ch duy nh\u1ea5t \u0111\u1ec3 ti\u1ebfp t\u1ee5c duy tr\u00ec tr\u1ea1i tr\u1ebb n\u00e0y l\u00e0 tr\u1ea3 \u0111\u01b0\u1ee3c 5.000 USD ti\u1ec1n thu\u1ebf trong v\u00f2ng 11 ng\u00e0y. Hai anh em nh\u00e0 Blues quy\u1ebft \u0111\u1ecbnh s\u1ebd gi\u00fap tr\u1ea1i tr\u1ebb b\u1eb1ng m\u1ed9t phi v\u1ee5 l\u1edbn nh\u1ea5t trong \u0111\u1eddi.",
    "metadata": {
        "page": 144,
        "index": 9,
        "time_craw": "2025-04-08 19:40:53"
    }
}