{
    "id": 1135869,
    "name": "Salome(2023)",
    "release_year": "05/13/2023 (ID",
    "genre": "['Phim Ch\u00ednh K\u1ecbch', 'Phim L\u00e3ng M\u1ea1n']",
    "runtime": "59m",
    "score": 100,
    "director": NaN,
    "status": "Released",
    "language": "Ti\u1ebfng Mo-tu",
    "budget": "-",
    "revenue": "-",
    "image": "https://media.themoviedb.org/t/p/w300_and_h450_bestv2/9R94k6pMdLWHwzxSSlKVrPo0EE3.jpg",
    "overview": "Kelas Bintang is back with this pack of drama called Salome.",
    "metadata": {
        "page": 46,
        "index": 2,
        "time_craw": "2025-04-08 16:33:40"
    }
}