{
    "id": 1495,
    "name": "V\u01b0\u01a1ng Qu\u1ed1c Thi\u00ean \u0110\u01b0\u1eddng(2005)",
    "release_year": "05/06/2005 (US",
    "genre": "['Phim Ch\u00ednh K\u1ecbch', 'Phim H\u00e0nh \u0110\u1ed9ng', 'Phim Phi\u00eau L\u01b0u', 'Phim L\u1ecbch S\u1eed', 'Phim Chi\u1ebfn Tranh']",
    "runtime": "2h 24m",
    "score": 70,
    "director": "Ridley Scott",
    "status": "Released",
    "language": "Ti\u1ebfng Anh",
    "budget": "$130,000,000.00",
    "revenue": "$218,100,001.00",
    "image": "https://media.themoviedb.org/t/p/w300_and_h450_bestv2/rNaBe4TwbMef71sgscqabpGKsxh.jpg",
    "overview": "Tr\u1eadn chi\u1ebfn v\u0129 \u0111\u1ea1i th\u00e0nh Jerusalem tr\u01b0\u1edbc qu\u00e2n \u0111\u1ed9i c\u1ee7a Vua Ai C\u1eadp Saladin \u0111\u01b0\u1ee3c ghi v\u00e0o l\u1ecbch s\u1eed nh\u01b0 m\u1ed9t tr\u1eadn chi\u1ebfn c\u1ee7a nh\u1eefng ng\u01b0\u1eddi s\u00f9ng \u0111\u1ea1o b\u1ea3o v\u1ec7 v\u01b0\u01a1ng qu\u1ed1c thi\u00ean \u0111\u00e0ng linh thi\u00eang c\u1ee7a h\u1ecd. B\u1ed9 phim c\u00e1c b\u1ea1n s\u1eafp xem s\u1ebd t\u00e1i hi\u1ec7n l\u1ecbch s\u1eed h\u00f9ng tr\u00e1ng v\u1edbi nh\u1eefng \u0111\u1ea1i c\u1ea3nh h\u00e0nh \u0111\u1ed9ng \u1ea5n t\u01b0\u1ee3ng c\u1ee7a tr\u1eadn \u0111\u1ea1i chi\u1ebfn l\u1ecbch s\u1eed. Nh\u00e2n v\u1eadt ch\u00ednh l\u00e0 ch\u00e0ng th\u1ee3 r\u00e8n Balian qu\u1ea3 c\u1ea3m, \u0111\u01b0\u1ee3c s\u1ed1 m\u1ec7nh d\u1eabn l\u1ed1i tr\u1edf th\u00e0nh ng\u01b0\u1eddi l\u00e3nh \u0111\u1ea1o qu\u00e2n \u0111\u1ed9i Jerusalem...",
    "metadata": {
        "page": 27,
        "index": 13,
        "time_craw": "2025-04-08 15:58:37"
    }
}