{
    "id": 760774,
    "name": "One Life(2023)",
    "release_year": "01/01/2024 (GB",
    "genre": "['Phim L\u1ecbch S\u1eed', 'Phim Ch\u00ednh K\u1ecbch']",
    "runtime": "1h 49m",
    "score": 78,
    "director": "James Hawes",
    "status": "Released",
    "language": "Ti\u1ebfng Anh",
    "budget": "-",
    "revenue": "$51,437,352.00",
    "image": "https://media.themoviedb.org/t/p/w300_and_h450_bestv2/yvnIWt2j8VnDgwKJE2VMiFMa2Qo.jpg",
    "overview": "British stockbroker Nicholas Winton visits Czechoslovakia in the 1930s and forms plans to assist in the rescue of Jewish children before the onset of World War II, in an operation that came to be known as the Kindertransport.",
    "metadata": {
        "page": 142,
        "index": 17,
        "time_craw": "2025-04-08 19:37:52"
    }
}